MANIFEST.in
README.rst
setup.py
flask_login_openerp/__init__.py
flask_login_openerp.egg-info/PKG-INFO
flask_login_openerp.egg-info/SOURCES.txt
flask_login_openerp.egg-info/dependency_links.txt
flask_login_openerp.egg-info/requires.txt
flask_login_openerp.egg-info/top_level.txt
flask_login_openerp/templates/openerp_login/base.html
flask_login_openerp/templates/openerp_login/login.html