Metadata-Version: 1.0
Name: flask-login-openerp
Version: 0.5.2
Summary: OpenERP Login for Flask using Flask-Login
Home-page: https://github.com/gisce/flask-login-openerp
Author: GISCE-TI, S.L.
Author-email: ti@gisce.net
License: MIT
Platform: UNKNOWN
